backpack/__init__.py
backpack/core.py
backpack/display.py
backpack/exceptions.py
backpack/features.py
backpack/insight.py
backpack/observer.py
backpack/options.py
backpack/scenarios.py
backpack/tools.py
backpack/web.py
locustio_backpack-0.3.0.dist-info/LICENSE
locustio_backpack-0.3.0.dist-info/METADATA
locustio_backpack-0.3.0.dist-info/WHEEL
locustio_backpack-0.3.0.dist-info/top_level.txt
locustio_backpack-0.3.0.dist-info/RECORD
