Metadata-Version: 2.1
Name: locustio-backpack
Version: 0.3.0
Summary: Locust Framework Extension
Home-page: UNKNOWN
Author: Alin-Marian Iuga
Author-email: alin.m.iga@gmail.com
License: UNKNOWN
Platform: UNKNOWN
Classifier: Development Status :: 3 - Alpha
Requires-Python: >=2.7
Requires-Dist: pandas (==0.23.4)
Requires-Dist: setuptools (==41.0.1)
Requires-Dist: wget (==3.2)
Requires-Dist: numpy (==1.15.4)
Requires-Dist: gevent (==1.3.7)
Requires-Dist: matplotlib (==2.2.4)
Requires-Dist: requests (==2.21.0)
Requires-Dist: locustio (==0.9.0)
